Metadata-Version: 2.1
Name: CookJoke
Version: 0.2.1
Summary: UNKNOWN
Home-page: https://github.com/cl1ckname/CookJoke
Author: Vasilev Ivan
Author-email: ivan.vasilev.cn@gmail.com
License: MIT
Keywords: humor
Platform: UNKNOWN
License-File: LICENSE
